easy_gravity/__init__.py
easy_gravity/gravity.py
easy_gravity-0.2.2.dist-info/METADATA
easy_gravity-0.2.2.dist-info/WHEEL
easy_gravity-0.2.2.dist-info/RECORD
