Metadata-Version: 2.3
Name: easy-gravity
Version: 0.2.2
Summary: Stupid lib to extract gravity from pycolmap reconstructions (or just numpy arrays)
Author-email: Johan Edstedt <johan.edstedt@liu.se>
Requires-Python: >=3.8
Requires-Dist: numpy<2
Requires-Dist: pycolmap==0.6.1
